ultimapy/__init__.py
ultimapy/sdk/__init__.py
ultimapy/sdk/animations.py
ultimapy/sdk/art.py
ultimapy/sdk/ascii_font.py
ultimapy/sdk/bodies.py
ultimapy/sdk/file_index.py
ultimapy/sdk/gumps.py
ultimapy/sdk/hues.py
ultimapy/sdk/skills.py
ultimapy/sdk/tile_data.py
ultimapy/sdk/utils.py
ultimapy/sdk/verdata.py
ultimapy/settings/__init__.py
ultimapy/settings/settings.py
ultimapy-0.0.24.dist-info/LICENSE
ultimapy-0.0.24.dist-info/METADATA
ultimapy-0.0.24.dist-info/WHEEL
ultimapy-0.0.24.dist-info/top_level.txt
ultimapy-0.0.24.dist-info/RECORD
