Metadata-Version: 2.1
Name: ultimapy
Version: 0.0.24
Summary: UltimaPy - Extract information and images from the UO client files
Home-page: https://github.com/jackuoll/ultima-py
Author: Jack Ward
Author-email: jackward84@gmail.com
License: Beerware
Classifier: Programming Language :: Python :: 3
Classifier: Operating System :: OS Independent
License-File: LICENSE
Requires-Dist: Pillow
Requires-Dist: imageio
